qoscope/__init__.py
qoscope/__main__.py
qoscope/app.py
qoscope/bridge.py
qoscope/controller.py
qoscope/device.py
qoscope/main_window.py
qoscope/main_window.qml
qoscope/workers.py
qoscope-1.0.0.dist-info/LICENSE
qoscope-1.0.0.dist-info/METADATA
qoscope-1.0.0.dist-info/WHEEL
qoscope-1.0.0.dist-info/entry_points.txt
qoscope-1.0.0.dist-info/top_level.txt
qoscope-1.0.0.dist-info/RECORD
