Metadata-Version: 2.1
Name: qoscope
Version: 1.0.0
Summary: A fast Arduino Oscilloscope
Home-page: https://github.com/sokolmarek/qoscope
Author: Marek Sokol
Author-email: mareksokol98@gmail.com
License: UNKNOWN
Platform: UNKNOWN
Classifier: Programming Language :: Python :: 3
Classifier: Operating System :: OS Independent
Classifier: Intended Audience :: Education
Classifier: Intended Audience :: Science/Research
Classifier: Topic :: Education
Classifier: Topic :: Scientific/Engineering
Requires-Python: >=3.8
License-File: LICENSE
Requires-Dist: numpy (>=1.17.0)
Requires-Dist: PySide6 (>=6.0.0)
Requires-Dist: pyserial (>=3.5)
